Workbook

Sheet Start Here
A1: Cash Flow Tracker
A2: A monthly 50/30/20 check-in from the DIY Wealth Framework.
A4: How to use it
A5: 1. | B5: On the Setup tab, enter your monthly take-home pay. Your 50/30/20 targets fill in.
A6: 2. | B6: On the Monthly tab, rename, add or delete categories to fit your life and tag each one Needs, Wants or Future You. The categories provided are only examples.
A7: 3. | B7: Once a month, enter what went to each category. Round numbers are fine: this is a check-in, not a ledger, so there is no need to track every coffee.
A8: 4. | B8: Read the summary at the top of Monthly: your savings rate, and a red flag when Needs take more than 50% of pay. If one month's pay was different, overwrite it in row 5.
A9: 5. | B9: After a raise, use the Raise Capture tab to see how much of it reached savings.
A11: Color key
B12: Green cells are yours to fill in. Everything else is a formula; leave it alone.
B14: Read the guide: Cash Flow Systems →
B15: Educational template only, not financial advice. No data leaves your spreadsheet.

Sheet Setup
A1: Setup
A2: Enter your monthly take-home pay once. Every month on the Monthly tab starts from it.
A5: Monthly take-home pay
A7: 50/30/20 targets
A8: Needs (50%) | B8: =ROUND($B$5*0.5,0) | C8: Housing, groceries, utilities, minimum debt payments.
A9: Wants (30%) | B9: =ROUND($B$5*0.3,0) | C9: Dining out, travel, entertainment.
A10: Future You (20%) | B10: =ROUND($B$5*0.2,0) | C10: Debt paydown above minimums, investing and saving.
A12: Each target is rounded to the nearest dollar on its own, so the three can add up to $1 more or less than your pay. The calculator on the site does the same.
A14: If Needs keep landing above 50%, you cannot budget your way out of it: you have a structural housing or transportation cost problem.

Sheet Monthly
A1: Monthly
A2: One row per category, not per transaction. Enter what went to each category each month.
A4: Summary | B4: Target | C4: Jan | D4: Feb | E4: Mar | F4: Apr | G4: May | H4: Jun | I4: Jul | J4: Aug | K4: Sep | L4: Oct | M4: Nov | N4: Dec | O4: Year to date
A5: Take-home pay | C5: =Setup!$B$5 | D5: =Setup!$B$5 | E5: =Setup!$B$5 | F5: =Setup!$B$5 | G5: =Setup!$B$5 | H5: =Setup!$B$5 | I5: =Setup!$B$5 | J5: =Setup!$B$5 | ... N5: =Setup!$B$5 | O5: =SUMPRODUCT((C6:N6+C7:N7+C8:N8>0)*C5:N5)
A6: Needs | B6: =Setup!B8 | C6: =SUMIF($B$16:$B$55,"Needs",C$16:C$55) | D6: =SUMIF($B$16:$B$55,"Needs",D$16:D$55) | E6: =SUMIF($B$16:$B$55,"Needs",E$16:E$55) | F6: =SUMIF($B$16:$B$55,"Needs",F$16:F$55) | G6: =SUMIF($B$16:$B$55,"Needs",G$16:G$55) | H6: =SUMIF($B$16:$B$55,"Needs",H$16:H$55) | I6: =SUMIF($B$16:$B$55,"Needs",I$16:I$55) | J6: =SUMIF($B$16:$B$55,"Needs",J$16:J$55) | ... O6: =SUMIF($B$16:$B$55,"Needs",O$16:O$55)
A7: Wants | B7: =Setup!B9 | C7: =SUMIF($B$16:$B$55,"Wants",C$16:C$55) | D7: =SUMIF($B$16:$B$55,"Wants",D$16:D$55) | E7: =SUMIF($B$16:$B$55,"Wants",E$16:E$55) | F7: =SUMIF($B$16:$B$55,"Wants",F$16:F$55) | G7: =SUMIF($B$16:$B$55,"Wants",G$16:G$55) | H7: =SUMIF($B$16:$B$55,"Wants",H$16:H$55) | I7: =SUMIF($B$16:$B$55,"Wants",I$16:I$55) | J7: =SUMIF($B$16:$B$55,"Wants",J$16:J$55) | ... O7: =SUMIF($B$16:$B$55,"Wants",O$16:O$55)
A8: Future You | B8: =Setup!B10 | C8: =SUMIF($B$16:$B$55,"Future You",C$16:C$55) | D8: =SUMIF($B$16:$B$55,"Future You",D$16:D$55) | E8: =SUMIF($B$16:$B$55,"Future You",E$16:E$55) | F8: =SUMIF($B$16:$B$55,"Future You",F$16:F$55) | G8: =SUMIF($B$16:$B$55,"Future You",G$16:G$55) | H8: =SUMIF($B$16:$B$55,"Future You",H$16:H$55) | I8: =SUMIF($B$16:$B$55,"Future You",I$16:I$55) | J8: =SUMIF($B$16:$B$55,"Future You",J$16:J$55) | ... O8: =SUMIF($B$16:$B$55,"Future You",O$16:O$55)
A9: Unassigned | C9: =IF(SUM(C6:C8)=0,"",C5-SUM(C6:C8)) | D9: =IF(SUM(D6:D8)=0,"",D5-SUM(D6:D8)) | E9: =IF(SUM(E6:E8)=0,"",E5-SUM(E6:E8)) | F9: =IF(SUM(F6:F8)=0,"",F5-SUM(F6:F8)) | G9: =IF(SUM(G6:G8)=0,"",G5-SUM(G6:G8)) | H9: =IF(SUM(H6:H8)=0,"",H5-SUM(H6:H8)) | I9: =IF(SUM(I6:I8)=0,"",I5-SUM(I6:I8)) | J9: =IF(SUM(J6:J8)=0,"",J5-SUM(J6:J8)) | ... O9: =IF(SUM(O6:O8)=0,"",O5-SUM(O6:O8))
A10: Needs % of pay | B10: 0.5 | C10: =IF(OR(SUM(C6:C8)=0,C$5<=0),"",C6/C$5) | D10: =IF(OR(SUM(D6:D8)=0,D$5<=0),"",D6/D$5) | E10: =IF(OR(SUM(E6:E8)=0,E$5<=0),"",E6/E$5) | F10: =IF(OR(SUM(F6:F8)=0,F$5<=0),"",F6/F$5) | G10: =IF(OR(SUM(G6:G8)=0,G$5<=0),"",G6/G$5) | H10: =IF(OR(SUM(H6:H8)=0,H$5<=0),"",H6/H$5) | I10: =IF(OR(SUM(I6:I8)=0,I$5<=0),"",I6/I$5) | J10: =IF(OR(SUM(J6:J8)=0,J$5<=0),"",J6/J$5) | ... O10: =IF(OR(SUM(O6:O8)=0,O$5<=0),"",O6/O$5)
A11: Wants % of pay | B11: 0.3 | C11: =IF(OR(SUM(C6:C8)=0,C$5<=0),"",C7/C$5) | D11: =IF(OR(SUM(D6:D8)=0,D$5<=0),"",D7/D$5) | E11: =IF(OR(SUM(E6:E8)=0,E$5<=0),"",E7/E$5) | F11: =IF(OR(SUM(F6:F8)=0,F$5<=0),"",F7/F$5) | G11: =IF(OR(SUM(G6:G8)=0,G$5<=0),"",G7/G$5) | H11: =IF(OR(SUM(H6:H8)=0,H$5<=0),"",H7/H$5) | I11: =IF(OR(SUM(I6:I8)=0,I$5<=0),"",I7/I$5) | J11: =IF(OR(SUM(J6:J8)=0,J$5<=0),"",J7/J$5) | ... O11: =IF(OR(SUM(O6:O8)=0,O$5<=0),"",O7/O$5)
A12: Future You % (savings rate) | B12: 0.2 | C12: =IF(OR(SUM(C6:C8)=0,C$5<=0),"",C8/C$5) | D12: =IF(OR(SUM(D6:D8)=0,D$5<=0),"",D8/D$5) | E12: =IF(OR(SUM(E6:E8)=0,E$5<=0),"",E8/E$5) | F12: =IF(OR(SUM(F6:F8)=0,F$5<=0),"",F8/F$5) | G12: =IF(OR(SUM(G6:G8)=0,G$5<=0),"",G8/G$5) | H12: =IF(OR(SUM(H6:H8)=0,H$5<=0),"",H8/H$5) | I12: =IF(OR(SUM(I6:I8)=0,I$5<=0),"",I8/I$5) | J12: =IF(OR(SUM(J6:J8)=0,J$5<=0),"",J8/J$5) | ... O12: =IF(OR(SUM(O6:O8)=0,O$5<=0),"",O8/O$5)
A13: Needs check | B13: Needs ≤ 50% | C13: =IF(C10="","",IF(C10>0.5,"Over 50%","OK")) | D13: =IF(D10="","",IF(D10>0.5,"Over 50%","OK")) | E13: =IF(E10="","",IF(E10>0.5,"Over 50%","OK")) | F13: =IF(F10="","",IF(F10>0.5,"Over 50%","OK")) | G13: =IF(G10="","",IF(G10>0.5,"Over 50%","OK")) | H13: =IF(H10="","",IF(H10>0.5,"Over 50%","OK")) | I13: =IF(I10="","",IF(I10>0.5,"Over 50%","OK")) | J13: =IF(J10="","",IF(J10>0.5,"Over 50%","OK")) | ... O13: =IF(O10="","",IF(O10>0.5,"Over 50%","OK"))
A15: Category | B15: Bucket | C15: Jan | D15: Feb | E15: Mar | F15: Apr | G15: May | H15: Jun | I15: Jul | J15: Aug | K15: Sep | L15: Oct | M15: Nov | N15: Dec | O15: Year
A16: Rent / mortgage | B16: Needs | O16: =IF(COUNT(C16:N16)=0,"",SUM(C16:N16))
A17: Groceries | B17: Needs | O17: =IF(COUNT(C17:N17)=0,"",SUM(C17:N17))
A18: Utilities | B18: Needs | O18: =IF(COUNT(C18:N18)=0,"",SUM(C18:N18))
A19: Insurance | B19: Needs | O19: =IF(COUNT(C19:N19)=0,"",SUM(C19:N19))
A20: Transportation | B20: Needs | O20: =IF(COUNT(C20:N20)=0,"",SUM(C20:N20))
A21: Minimum debt payments | B21: Needs | O21: =IF(COUNT(C21:N21)=0,"",SUM(C21:N21))
A22: Dining out | B22: Wants | O22: =IF(COUNT(C22:N22)=0,"",SUM(C22:N22))
A23: Travel | B23: Wants | O23: =IF(COUNT(C23:N23)=0,"",SUM(C23:N23))
A24: Entertainment | B24: Wants | O24: =IF(COUNT(C24:N24)=0,"",SUM(C24:N24))
A25: Subscriptions | B25: Wants | O25: =IF(COUNT(C25:N25)=0,"",SUM(C25:N25))
A26: Shopping | B26: Wants | O26: =IF(COUNT(C26:N26)=0,"",SUM(C26:N26))
A27: Investing sweep | B27: Future You | O27: =IF(COUNT(C27:N27)=0,"",SUM(C27:N27))
... A29: Extra debt paydown | B29: Future You | O29: =IF(COUNT(C29:N29)=0,"",SUM(C29:N29))
O30: =IF(COUNT(C30:N30)=0,"",SUM(C30:N30))
O31: =IF(COUNT(C31:N31)=0,"",SUM(C31:N31))
O32: =IF(COUNT(C32:N32)=0,"",SUM(C32:N32))
O33: =IF(COUNT(C33:N33)=0,"",SUM(C33:N33))
O34: =IF(COUNT(C34:N34)=0,"",SUM(C34:N34))
O35: =IF(COUNT(C35:N35)=0,"",SUM(C35:N35))
O36: =IF(COUNT(C36:N36)=0,"",SUM(C36:N36))
O37: =IF(COUNT(C37:N37)=0,"",SUM(C37:N37))
O38: =IF(COUNT(C38:N38)=0,"",SUM(C38:N38))
O39: =IF(COUNT(C39:N39)=0,"",SUM(C39:N39))
O40: =IF(COUNT(C40:N40)=0,"",SUM(C40:N40))
O41: =IF(COUNT(C41:N41)=0,"",SUM(C41:N41))
... O55: =IF(COUNT(C55:N55)=0,"",SUM(C55:N55))

Sheet Raise Capture
A1: Raise Capture
A2: How much of your last raise reached savings? Use annual figures from two points in time.
A5: Past annual income
A6: Current annual income
A7: Past annual savings
A8: Current annual savings
A10: Income increase | B10: =IF(COUNT(B5:B8)<4,"",B6-B5)
A11: Savings increase | B11: =IF(COUNT(B5:B8)<4,"",B8-B7)
A12: Capture rate | B12: =IF(COUNT(B5:B8)<4,"",IF(B10>0,B11/B10,0))
A14: Verdict | B14: =IF(COUNT(B5:B8)<4,"Enter all four numbers above",IF(B10<=0,"Income stagnant or decreased",IF(B12>=0.5,"Excellent wealth capture",IF(B12>=0.2,"Moderate creep","Severe lifestyle creep"))))
A15: What to do | B15: =IF(COUNT(B5:B8)<4,"",IF(B10<=0,"Your income has not increased during this period. Focus on increasing your earning power or reducing baseline expenses.",IF(B12>=0.5,"Your cash flow systems are successfully resisting lifestyle inflation.",IF(B12>=0.2,"You are hitting the baseline 20% target, but your lifestyle is inflating noticeably. Consider routing your next raise entirely to investments.","You are spending almost all of your new money. You urgently need an intermediate Holding Account to trap raises before they hit your checking account."))))
A19: Thresholds: 50% or more is excellent, 20–49% is moderate, under 20% is severe.
