Workbook

Sheet Start Here
A1: Net Worth Dashboard
A2: A monthly snapshot of everything you own and owe, from the DIY Wealth Framework.
A4: How to use it
A5: 1. | B5: On the Accounts tab, list every asset and debt once and pick its type. The accounts provided are only examples: rename, add or delete rows.
A6: 2. | B6: Once a month, go to the Snapshots tab and enter each balance in that month's column. Enter debts as positive numbers.
A7: 3. | B7: Set your first month in Snapshots cell C4. The next 23 months fill in after it.
A8: 4. | B8: On the Dashboard tab, enter your monthly essential expenses once to see how many months your cash covers.
A9: 5. | B9: Read the Dashboard: net worth, liquid net worth, debt-to-asset ratio, asset mix and the trend. It always shows the latest month you filled in.
A11: Color key
B12: Green cells are yours to fill in. Everything else is a formula; leave it alone.
B14: Read the guide: Financial Defense →
B15: Educational template only, not financial advice. No data leaves your spreadsheet.

Sheet Dashboard
A1: Dashboard
A2: Your latest month at a glance. Nothing to enter here except monthly essentials.
A4: Latest month | B4: =IFERROR(INDEX(Snapshots!$C$4:$Z$4,MATCH(2,Snapshots!$C$53:$Z$53)),"No balances yet")
A6: Where you stand | E6: Month | F6: Net worth
A7: Net worth | B7: =IFERROR(INDEX(Snapshots!$C$49:$Z$49,MATCH(2,Snapshots!$C$53:$Z$53)),"") | E7: =INDEX(Snapshots!$C$4:$Z$4,1) | F7: =IF(INDEX(Snapshots!$C$53:$Z$53,1)=1,INDEX(Snapshots!$C$49:$Z$49,1),NA())
A8: Total assets | B8: =IFERROR(INDEX(Snapshots!$C$47:$Z$47,MATCH(2,Snapshots!$C$53:$Z$53)),"") | E8: =INDEX(Snapshots!$C$4:$Z$4,2) | F8: =IF(INDEX(Snapshots!$C$53:$Z$53,2)=1,INDEX(Snapshots!$C$49:$Z$49,2),NA())
A9: Total debts | B9: =IFERROR(INDEX(Snapshots!$C$48:$Z$48,MATCH(2,Snapshots!$C$53:$Z$53)),"") | E9: =INDEX(Snapshots!$C$4:$Z$4,3) | F9: =IF(INDEX(Snapshots!$C$53:$Z$53,3)=1,INDEX(Snapshots!$C$49:$Z$49,3),NA())
A10: Liquid net worth | B10: =IFERROR(INDEX(Snapshots!$C$51:$Z$51,MATCH(2,Snapshots!$C$53:$Z$53)),"") | E10: =INDEX(Snapshots!$C$4:$Z$4,4) | F10: =IF(INDEX(Snapshots!$C$53:$Z$53,4)=1,INDEX(Snapshots!$C$49:$Z$49,4),NA())
A11: Change since previous month | B11: =IFERROR(IF(INDEX(Snapshots!$C$53:$Z$53,MATCH(2,Snapshots!$C$53:$Z$53)-1)=1,B7-INDEX(Snapshots!$C$49:$Z$49,MATCH(2,Snapshots!$C$53:$Z$53)-1),""),"") | E11: =INDEX(Snapshots!$C$4:$Z$4,5) | F11: =IF(INDEX(Snapshots!$C$53:$Z$53,5)=1,INDEX(Snapshots!$C$49:$Z$49,5),NA())
A12: Debt-to-asset ratio | B12: =IF(AND(ISNUMBER(B8),B8>0),B9/B8,"") | E12: =INDEX(Snapshots!$C$4:$Z$4,6) | F12: =IF(INDEX(Snapshots!$C$53:$Z$53,6)=1,INDEX(Snapshots!$C$49:$Z$49,6),NA())
A13: Liquid net worth counts cash and taxable investing, minus all debts. | E13: =INDEX(Snapshots!$C$4:$Z$4,7) | F13: =IF(INDEX(Snapshots!$C$53:$Z$53,7)=1,INDEX(Snapshots!$C$49:$Z$49,7),NA())
E14: =INDEX(Snapshots!$C$4:$Z$4,8) | F14: =IF(INDEX(Snapshots!$C$53:$Z$53,8)=1,INDEX(Snapshots!$C$49:$Z$49,8),NA())
A15: Emergency reserve | E15: =INDEX(Snapshots!$C$4:$Z$4,9) | F15: =IF(INDEX(Snapshots!$C$53:$Z$53,9)=1,INDEX(Snapshots!$C$49:$Z$49,9),NA())
A16: Monthly essential expenses | E16: =INDEX(Snapshots!$C$4:$Z$4,10) | F16: =IF(INDEX(Snapshots!$C$53:$Z$53,10)=1,INDEX(Snapshots!$C$49:$Z$49,10),NA())
A17: Cash on hand | B17: =IFERROR(INDEX(Snapshots!$C$52:$Z$52,MATCH(2,Snapshots!$C$53:$Z$53)),"") | E17: =INDEX(Snapshots!$C$4:$Z$4,11) | F17: =IF(INDEX(Snapshots!$C$53:$Z$53,11)=1,INDEX(Snapshots!$C$49:$Z$49,11),NA())
A18: Months of expenses covered | B18: =IF(AND(ISNUMBER(B16),B16>0,ISNUMBER(B17)),B17/B16,"") | E18: =INDEX(Snapshots!$C$4:$Z$4,12) | F18: =IF(INDEX(Snapshots!$C$53:$Z$53,12)=1,INDEX(Snapshots!$C$49:$Z$49,12),NA())
A19: Size your target with the Emergency Reserve calculator in section 1. | E19: =INDEX(Snapshots!$C$4:$Z$4,13) | F19: =IF(INDEX(Snapshots!$C$53:$Z$53,13)=1,INDEX(Snapshots!$C$49:$Z$49,13),NA())
E20: =INDEX(Snapshots!$C$4:$Z$4,14) | F20: =IF(INDEX(Snapshots!$C$53:$Z$53,14)=1,INDEX(Snapshots!$C$49:$Z$49,14),NA())
A21: Asset mix (latest month) | E21: =INDEX(Snapshots!$C$4:$Z$4,15) | F21: =IF(INDEX(Snapshots!$C$53:$Z$53,15)=1,INDEX(Snapshots!$C$49:$Z$49,15),NA())
A22: Type | B22: Balance | C22: Share | E22: =INDEX(Snapshots!$C$4:$Z$4,16) | F22: =IF(INDEX(Snapshots!$C$53:$Z$53,16)=1,INDEX(Snapshots!$C$49:$Z$49,16),NA())
A23: Cash | B23: =IFERROR(SUMIFS(INDEX(Snapshots!$C$5:$Z$44,0,MATCH(2,Snapshots!$C$53:$Z$53)),Accounts!$B$5:$B$44,A23),"") | C23: =IF(AND(ISNUMBER(B23),ISNUMBER($B$8),$B$8>0),B23/$B$8,"") | E23: =INDEX(Snapshots!$C$4:$Z$4,17) | F23: =IF(INDEX(Snapshots!$C$53:$Z$53,17)=1,INDEX(Snapshots!$C$49:$Z$49,17),NA())
A24: Taxable investing | B24: =IFERROR(SUMIFS(INDEX(Snapshots!$C$5:$Z$44,0,MATCH(2,Snapshots!$C$53:$Z$53)),Accounts!$B$5:$B$44,A24),"") | C24: =IF(AND(ISNUMBER(B24),ISNUMBER($B$8),$B$8>0),B24/$B$8,"") | E24: =INDEX(Snapshots!$C$4:$Z$4,18) | F24: =IF(INDEX(Snapshots!$C$53:$Z$53,18)=1,INDEX(Snapshots!$C$49:$Z$49,18),NA())
A25: Retirement | B25: =IFERROR(SUMIFS(INDEX(Snapshots!$C$5:$Z$44,0,MATCH(2,Snapshots!$C$53:$Z$53)),Accounts!$B$5:$B$44,A25),"") | C25: =IF(AND(ISNUMBER(B25),ISNUMBER($B$8),$B$8>0),B25/$B$8,"") | E25: =INDEX(Snapshots!$C$4:$Z$4,19) | F25: =IF(INDEX(Snapshots!$C$53:$Z$53,19)=1,INDEX(Snapshots!$C$49:$Z$49,19),NA())
A26: HSA | B26: =IFERROR(SUMIFS(INDEX(Snapshots!$C$5:$Z$44,0,MATCH(2,Snapshots!$C$53:$Z$53)),Accounts!$B$5:$B$44,A26),"") | C26: =IF(AND(ISNUMBER(B26),ISNUMBER($B$8),$B$8>0),B26/$B$8,"") | E26: =INDEX(Snapshots!$C$4:$Z$4,20) | F26: =IF(INDEX(Snapshots!$C$53:$Z$53,20)=1,INDEX(Snapshots!$C$49:$Z$49,20),NA())
A27: Real estate | B27: =IFERROR(SUMIFS(INDEX(Snapshots!$C$5:$Z$44,0,MATCH(2,Snapshots!$C$53:$Z$53)),Accounts!$B$5:$B$44,A27),"") | C27: =IF(AND(ISNUMBER(B27),ISNUMBER($B$8),$B$8>0),B27/$B$8,"") | E27: =INDEX(Snapshots!$C$4:$Z$4,21) | F27: =IF(INDEX(Snapshots!$C$53:$Z$53,21)=1,INDEX(Snapshots!$C$49:$Z$49,21),NA())
A28: Vehicle | B28: =IFERROR(SUMIFS(INDEX(Snapshots!$C$5:$Z$44,0,MATCH(2,Snapshots!$C$53:$Z$53)),Accounts!$B$5:$B$44,A28),"") | C28: =IF(AND(ISNUMBER(B28),ISNUMBER($B$8),$B$8>0),B28/$B$8,"") | E28: =INDEX(Snapshots!$C$4:$Z$4,22) | F28: =IF(INDEX(Snapshots!$C$53:$Z$53,22)=1,INDEX(Snapshots!$C$49:$Z$49,22),NA())
A29: Other asset | B29: =IFERROR(SUMIFS(INDEX(Snapshots!$C$5:$Z$44,0,MATCH(2,Snapshots!$C$53:$Z$53)),Accounts!$B$5:$B$44,A29),"") | C29: =IF(AND(ISNUMBER(B29),ISNUMBER($B$8),$B$8>0),B29/$B$8,"") | E29: =INDEX(Snapshots!$C$4:$Z$4,23) | F29: =IF(INDEX(Snapshots!$C$53:$Z$53,23)=1,INDEX(Snapshots!$C$49:$Z$49,23),NA())
E30: =INDEX(Snapshots!$C$4:$Z$4,24) | F30: =IF(INDEX(Snapshots!$C$53:$Z$53,24)=1,INDEX(Snapshots!$C$49:$Z$49,24),NA())

Sheet Accounts
A1: Accounts
A2: List every asset and debt once. Balances go on the Snapshots tab.
A4: Account | B4: Type | C4: Kind | D4: Liquid | E4: Notes
A5: Checking | B5: Cash | C5: =IF(B5="","",VLOOKUP(B5,Lists!$A$5:$C$16,2,FALSE)) | D5: =IF(B5="","",IF(VLOOKUP(B5,Lists!$A$5:$C$16,3,FALSE)="Yes","Yes",""))
A6: High-yield savings | B6: Cash | C6: =IF(B6="","",VLOOKUP(B6,Lists!$A$5:$C$16,2,FALSE)) | D6: =IF(B6="","",IF(VLOOKUP(B6,Lists!$A$5:$C$16,3,FALSE)="Yes","Yes",""))
A7: Brokerage | B7: Taxable investing | C7: =IF(B7="","",VLOOKUP(B7,Lists!$A$5:$C$16,2,FALSE)) | D7: =IF(B7="","",IF(VLOOKUP(B7,Lists!$A$5:$C$16,3,FALSE)="Yes","Yes",""))
A8: 401(k) | B8: Retirement | C8: =IF(B8="","",VLOOKUP(B8,Lists!$A$5:$C$16,2,FALSE)) | D8: =IF(B8="","",IF(VLOOKUP(B8,Lists!$A$5:$C$16,3,FALSE)="Yes","Yes",""))
A9: Roth IRA | B9: Retirement | C9: =IF(B9="","",VLOOKUP(B9,Lists!$A$5:$C$16,2,FALSE)) | D9: =IF(B9="","",IF(VLOOKUP(B9,Lists!$A$5:$C$16,3,FALSE)="Yes","Yes",""))
A10: HSA | B10: HSA | C10: =IF(B10="","",VLOOKUP(B10,Lists!$A$5:$C$16,2,FALSE)) | D10: =IF(B10="","",IF(VLOOKUP(B10,Lists!$A$5:$C$16,3,FALSE)="Yes","Yes",""))
A11: Home | B11: Real estate | C11: =IF(B11="","",VLOOKUP(B11,Lists!$A$5:$C$16,2,FALSE)) | D11: =IF(B11="","",IF(VLOOKUP(B11,Lists!$A$5:$C$16,3,FALSE)="Yes","Yes",""))
A12: Car | B12: Vehicle | C12: =IF(B12="","",VLOOKUP(B12,Lists!$A$5:$C$16,2,FALSE)) | D12: =IF(B12="","",IF(VLOOKUP(B12,Lists!$A$5:$C$16,3,FALSE)="Yes","Yes",""))
A13: Mortgage | B13: Mortgage | C13: =IF(B13="","",VLOOKUP(B13,Lists!$A$5:$C$16,2,FALSE)) | D13: =IF(B13="","",IF(VLOOKUP(B13,Lists!$A$5:$C$16,3,FALSE)="Yes","Yes",""))
A14: Auto loan | B14: Auto loan | C14: =IF(B14="","",VLOOKUP(B14,Lists!$A$5:$C$16,2,FALSE)) | D14: =IF(B14="","",IF(VLOOKUP(B14,Lists!$A$5:$C$16,3,FALSE)="Yes","Yes",""))
A15: Student loan | B15: Student loan | C15: =IF(B15="","",VLOOKUP(B15,Lists!$A$5:$C$16,2,FALSE)) | D15: =IF(B15="","",IF(VLOOKUP(B15,Lists!$A$5:$C$16,3,FALSE)="Yes","Yes",""))
A16: Credit card | B16: Credit card | C16: =IF(B16="","",VLOOKUP(B16,Lists!$A$5:$C$16,2,FALSE)) | D16: =IF(B16="","",IF(VLOOKUP(B16,Lists!$A$5:$C$16,3,FALSE)="Yes","Yes",""))
C17: =IF(B17="","",VLOOKUP(B17,Lists!$A$5:$C$16,2,FALSE)) | D17: =IF(B17="","",IF(VLOOKUP(B17,Lists!$A$5:$C$16,3,FALSE)="Yes","Yes",""))
C18: =IF(B18="","",VLOOKUP(B18,Lists!$A$5:$C$16,2,FALSE)) | D18: =IF(B18="","",IF(VLOOKUP(B18,Lists!$A$5:$C$16,3,FALSE)="Yes","Yes",""))
C19: =IF(B19="","",VLOOKUP(B19,Lists!$A$5:$C$16,2,FALSE)) | D19: =IF(B19="","",IF(VLOOKUP(B19,Lists!$A$5:$C$16,3,FALSE)="Yes","Yes",""))
C20: =IF(B20="","",VLOOKUP(B20,Lists!$A$5:$C$16,2,FALSE)) | D20: =IF(B20="","",IF(VLOOKUP(B20,Lists!$A$5:$C$16,3,FALSE)="Yes","Yes",""))
C21: =IF(B21="","",VLOOKUP(B21,Lists!$A$5:$C$16,2,FALSE)) | D21: =IF(B21="","",IF(VLOOKUP(B21,Lists!$A$5:$C$16,3,FALSE)="Yes","Yes",""))
C22: =IF(B22="","",VLOOKUP(B22,Lists!$A$5:$C$16,2,FALSE)) | D22: =IF(B22="","",IF(VLOOKUP(B22,Lists!$A$5:$C$16,3,FALSE)="Yes","Yes",""))
C23: =IF(B23="","",VLOOKUP(B23,Lists!$A$5:$C$16,2,FALSE)) | D23: =IF(B23="","",IF(VLOOKUP(B23,Lists!$A$5:$C$16,3,FALSE)="Yes","Yes",""))
C24: =IF(B24="","",VLOOKUP(B24,Lists!$A$5:$C$16,2,FALSE)) | D24: =IF(B24="","",IF(VLOOKUP(B24,Lists!$A$5:$C$16,3,FALSE)="Yes","Yes",""))
C25: =IF(B25="","",VLOOKUP(B25,Lists!$A$5:$C$16,2,FALSE)) | D25: =IF(B25="","",IF(VLOOKUP(B25,Lists!$A$5:$C$16,3,FALSE)="Yes","Yes",""))
C26: =IF(B26="","",VLOOKUP(B26,Lists!$A$5:$C$16,2,FALSE)) | D26: =IF(B26="","",IF(VLOOKUP(B26,Lists!$A$5:$C$16,3,FALSE)="Yes","Yes",""))
C27: =IF(B27="","",VLOOKUP(B27,Lists!$A$5:$C$16,2,FALSE)) | D27: =IF(B27="","",IF(VLOOKUP(B27,Lists!$A$5:$C$16,3,FALSE)="Yes","Yes",""))
C28: =IF(B28="","",VLOOKUP(B28,Lists!$A$5:$C$16,2,FALSE)) | D28: =IF(B28="","",IF(VLOOKUP(B28,Lists!$A$5:$C$16,3,FALSE)="Yes","Yes",""))
... C44: =IF(B44="","",VLOOKUP(B44,Lists!$A$5:$C$16,2,FALSE)) | D44: =IF(B44="","",IF(VLOOKUP(B44,Lists!$A$5:$C$16,3,FALSE)="Yes","Yes",""))
A46: Enter debts as positive balances. The Kind column subtracts them for you.

Sheet Snapshots
A1: Snapshots
A2: Once a month, enter each balance. Set your first month in C4; the rest follow.
A4: Account | B4: Type | C4: 46023 | D4: =EDATE(C4,1) | E4: =EDATE(D4,1) | F4: =EDATE(E4,1) | G4: =EDATE(F4,1) | H4: =EDATE(G4,1) | I4: =EDATE(H4,1) | J4: =EDATE(I4,1) | K4: =EDATE(J4,1) | ... Z4: =EDATE(Y4,1)
A5: =IF(Accounts!A5="","",Accounts!A5) | B5: =IF(Accounts!B5="","",Accounts!B5)
A6: =IF(Accounts!A6="","",Accounts!A6) | B6: =IF(Accounts!B6="","",Accounts!B6)
A7: =IF(Accounts!A7="","",Accounts!A7) | B7: =IF(Accounts!B7="","",Accounts!B7)
A8: =IF(Accounts!A8="","",Accounts!A8) | B8: =IF(Accounts!B8="","",Accounts!B8)
A9: =IF(Accounts!A9="","",Accounts!A9) | B9: =IF(Accounts!B9="","",Accounts!B9)
A10: =IF(Accounts!A10="","",Accounts!A10) | B10: =IF(Accounts!B10="","",Accounts!B10)
A11: =IF(Accounts!A11="","",Accounts!A11) | B11: =IF(Accounts!B11="","",Accounts!B11)
A12: =IF(Accounts!A12="","",Accounts!A12) | B12: =IF(Accounts!B12="","",Accounts!B12)
A13: =IF(Accounts!A13="","",Accounts!A13) | B13: =IF(Accounts!B13="","",Accounts!B13)
A14: =IF(Accounts!A14="","",Accounts!A14) | B14: =IF(Accounts!B14="","",Accounts!B14)
A15: =IF(Accounts!A15="","",Accounts!A15) | B15: =IF(Accounts!B15="","",Accounts!B15)
A16: =IF(Accounts!A16="","",Accounts!A16) | B16: =IF(Accounts!B16="","",Accounts!B16)
... A44: =IF(Accounts!A44="","",Accounts!A44) | B44: =IF(Accounts!B44="","",Accounts!B44)
A46: Totals
A47: Total assets | C47: =IF(C$53=1,SUMIFS(C$5:C$44,Accounts!$C$5:$C$44,"Asset"),"") | D47: =IF(D$53=1,SUMIFS(D$5:D$44,Accounts!$C$5:$C$44,"Asset"),"") | E47: =IF(E$53=1,SUMIFS(E$5:E$44,Accounts!$C$5:$C$44,"Asset"),"") | F47: =IF(F$53=1,SUMIFS(F$5:F$44,Accounts!$C$5:$C$44,"Asset"),"") | G47: =IF(G$53=1,SUMIFS(G$5:G$44,Accounts!$C$5:$C$44,"Asset"),"") | H47: =IF(H$53=1,SUMIFS(H$5:H$44,Accounts!$C$5:$C$44,"Asset"),"") | I47: =IF(I$53=1,SUMIFS(I$5:I$44,Accounts!$C$5:$C$44,"Asset"),"") | J47: =IF(J$53=1,SUMIFS(J$5:J$44,Accounts!$C$5:$C$44,"Asset"),"") | ... Z47: =IF(Z$53=1,SUMIFS(Z$5:Z$44,Accounts!$C$5:$C$44,"Asset"),"")
A48: Total debts | C48: =IF(C$53=1,SUMIFS(C$5:C$44,Accounts!$C$5:$C$44,"Debt"),"") | D48: =IF(D$53=1,SUMIFS(D$5:D$44,Accounts!$C$5:$C$44,"Debt"),"") | E48: =IF(E$53=1,SUMIFS(E$5:E$44,Accounts!$C$5:$C$44,"Debt"),"") | F48: =IF(F$53=1,SUMIFS(F$5:F$44,Accounts!$C$5:$C$44,"Debt"),"") | G48: =IF(G$53=1,SUMIFS(G$5:G$44,Accounts!$C$5:$C$44,"Debt"),"") | H48: =IF(H$53=1,SUMIFS(H$5:H$44,Accounts!$C$5:$C$44,"Debt"),"") | I48: =IF(I$53=1,SUMIFS(I$5:I$44,Accounts!$C$5:$C$44,"Debt"),"") | J48: =IF(J$53=1,SUMIFS(J$5:J$44,Accounts!$C$5:$C$44,"Debt"),"") | ... Z48: =IF(Z$53=1,SUMIFS(Z$5:Z$44,Accounts!$C$5:$C$44,"Debt"),"")
A49: Net worth | C49: =IF(C$53=1,C47-C48,"") | D49: =IF(D$53=1,D47-D48,"") | E49: =IF(E$53=1,E47-E48,"") | F49: =IF(F$53=1,F47-F48,"") | G49: =IF(G$53=1,G47-G48,"") | H49: =IF(H$53=1,H47-H48,"") | I49: =IF(I$53=1,I47-I48,"") | J49: =IF(J$53=1,J47-J48,"") | ... Z49: =IF(Z$53=1,Z47-Z48,"")
A50: Liquid assets | C50: =IF(C$53=1,SUMIFS(C$5:C$44,Accounts!$D$5:$D$44,"Yes"),"") | D50: =IF(D$53=1,SUMIFS(D$5:D$44,Accounts!$D$5:$D$44,"Yes"),"") | E50: =IF(E$53=1,SUMIFS(E$5:E$44,Accounts!$D$5:$D$44,"Yes"),"") | F50: =IF(F$53=1,SUMIFS(F$5:F$44,Accounts!$D$5:$D$44,"Yes"),"") | G50: =IF(G$53=1,SUMIFS(G$5:G$44,Accounts!$D$5:$D$44,"Yes"),"") | H50: =IF(H$53=1,SUMIFS(H$5:H$44,Accounts!$D$5:$D$44,"Yes"),"") | I50: =IF(I$53=1,SUMIFS(I$5:I$44,Accounts!$D$5:$D$44,"Yes"),"") | J50: =IF(J$53=1,SUMIFS(J$5:J$44,Accounts!$D$5:$D$44,"Yes"),"") | ... Z50: =IF(Z$53=1,SUMIFS(Z$5:Z$44,Accounts!$D$5:$D$44,"Yes"),"")
A51: Liquid net worth | C51: =IF(C$53=1,C50-C48,"") | D51: =IF(D$53=1,D50-D48,"") | E51: =IF(E$53=1,E50-E48,"") | F51: =IF(F$53=1,F50-F48,"") | G51: =IF(G$53=1,G50-G48,"") | H51: =IF(H$53=1,H50-H48,"") | I51: =IF(I$53=1,I50-I48,"") | J51: =IF(J$53=1,J50-J48,"") | ... Z51: =IF(Z$53=1,Z50-Z48,"")
A52: Cash | C52: =IF(C$53=1,SUMIFS(C$5:C$44,Accounts!$B$5:$B$44,"Cash"),"") | D52: =IF(D$53=1,SUMIFS(D$5:D$44,Accounts!$B$5:$B$44,"Cash"),"") | E52: =IF(E$53=1,SUMIFS(E$5:E$44,Accounts!$B$5:$B$44,"Cash"),"") | F52: =IF(F$53=1,SUMIFS(F$5:F$44,Accounts!$B$5:$B$44,"Cash"),"") | G52: =IF(G$53=1,SUMIFS(G$5:G$44,Accounts!$B$5:$B$44,"Cash"),"") | H52: =IF(H$53=1,SUMIFS(H$5:H$44,Accounts!$B$5:$B$44,"Cash"),"") | I52: =IF(I$53=1,SUMIFS(I$5:I$44,Accounts!$B$5:$B$44,"Cash"),"") | J52: =IF(J$53=1,SUMIFS(J$5:J$44,Accounts!$B$5:$B$44,"Cash"),"") | ... Z52: =IF(Z$53=1,SUMIFS(Z$5:Z$44,Accounts!$B$5:$B$44,"Cash"),"")
A53: Month has balances | B53: (1 = yes; used by Dashboard) | C53: =IF(COUNT(C$5:C$44)>0,1,"") | D53: =IF(COUNT(D$5:D$44)>0,1,"") | E53: =IF(COUNT(E$5:E$44)>0,1,"") | F53: =IF(COUNT(F$5:F$44)>0,1,"") | G53: =IF(COUNT(G$5:G$44)>0,1,"") | H53: =IF(COUNT(H$5:H$44)>0,1,"") | I53: =IF(COUNT(I$5:I$44)>0,1,"") | J53: =IF(COUNT(J$5:J$44)>0,1,"") | ... Z53: =IF(COUNT(Z$5:Z$44)>0,1,"")

Sheet Lists
A1: Lists
A2: Account types used by the Accounts tab. Edit with care.
A4: Type | B4: Kind | C4: Liquid
A5: Cash | B5: Asset | C5: Yes
A6: Taxable investing | B6: Asset | C6: Yes
A7: Retirement | B7: Asset | C7: No
A8: HSA | B8: Asset | C8: No
A9: Real estate | B9: Asset | C9: No
A10: Vehicle | B10: Asset | C10: No
A11: Other asset | B11: Asset | C11: No
A12: Mortgage | B12: Debt
A13: Student loan | B13: Debt
A14: Auto loan | B14: Debt
A15: Credit card | B15: Debt
A16: Other debt | B16: Debt
